octo_pipeline_python/backends/s3/__init__.py
octo_pipeline_python/backends/s3/s3_backend.py
octo_pipeline_python/backends/s3/actions/__init__.py
octo_pipeline_python/backends/s3/actions/s3_download.py
octo_pipeline_python/backends/s3/actions/s3_upload.py
octo_pipeline_python/backends/s3/models/__init__.py
octo_pipeline_python/backends/s3/models/s3_model.py
octo_pipeline_backend_s3_python-1.3.2.dist-info/LICENSE.txt
octo_pipeline_backend_s3_python-1.3.2.dist-info/METADATA
octo_pipeline_backend_s3_python-1.3.2.dist-info/README.md
octo_pipeline_backend_s3_python-1.3.2.dist-info/WHEEL
octo_pipeline_backend_s3_python-1.3.2.dist-info/top_level.txt
octo_pipeline_backend_s3_python-1.3.2.dist-info/RECORD
